Scrapy_UserAgents-0.0.1.dist-info/DESCRIPTION.rst
Scrapy_UserAgents-0.0.1.dist-info/METADATA
Scrapy_UserAgents-0.0.1.dist-info/RECORD
Scrapy_UserAgents-0.0.1.dist-info/WHEEL
Scrapy_UserAgents-0.0.1.dist-info/metadata.json
Scrapy_UserAgents-0.0.1.dist-info/top_level.txt
scrapy_useragents/VERSION
scrapy_useragents/__init__.py
scrapy_useragents/downloadermiddlewares/__init__.py
scrapy_useragents/downloadermiddlewares/useragents.py
