Metadata-Version: 1.1
Name: Scrapy-UserAgents
Version: 0.0.1
Summary: A middleware to change user-agent in request for Scrapy
Home-page: https://github.com/grammy-jiang/scrapy-useragents
Author: Grammy Jiang
Author-email: grammy.jiang@gmail.com
License: BSD
Platform: UNKNOWN
Classifier: Framework :: Scrapy
Classifier: Development Status :: 2 - Pre-Alpha
Classifier: Environment :: Plugins
Classifier: Intended Audience :: Developers
Classifier: License :: OSI Approved :: BSD License
Classifier: Operating System :: OS Independent
Classifier: Programming Language :: Python
Classifier: Programming Language :: Python :: 2
Classifier: Programming Language :: Python :: 2.7
Classifier: Programming Language :: Python :: 3
Classifier: Programming Language :: Python :: 3.3
Classifier: Programming Language :: Python :: 3.4
Classifier: Programming Language :: Python :: 3.5
Classifier: Programming Language :: Python :: 3.6
Classifier: Topic :: Internet :: WWW/HTTP
Classifier: Topic :: Software Development :: Libraries :: Python Modules
